smartcare/Brain.py
smartcare/Config.py
smartcare/ConfigEnum.py
smartcare/Image.py
smartcare/__init__.py
smartcare/model/modelCNN-1605022224.h5
smartcare-1.0.2.dist-info/METADATA
smartcare-1.0.2.dist-info/WHEEL
smartcare-1.0.2.dist-info/top_level.txt
smartcare-1.0.2.dist-info/RECORD
