Metadata-Version: 2.1
Name: smartcare
Version: 1.0.2
Summary: Elderly wandering prediction AI
Home-page: UNKNOWN
Author: Rafael Faustini
Author-email: <contato@rafaelfaustini.com.br>
License: UNKNOWN
Keywords: machinelearning,paper,smartcare,cnn,artificial inteligence,alzheimer,health
Platform: UNKNOWN
Classifier: Development Status :: 1 - Planning
Classifier: Intended Audience :: Developers
Classifier: Programming Language :: Python :: 3
Classifier: Operating System :: Unix
Classifier: Operating System :: MacOS :: MacOS X
Classifier: Operating System :: Microsoft :: Windows
Requires-Dist: tensorflow
Requires-Dist: keras
Requires-Dist: pillow
Requires-Dist: tensorboard-plugin-profile
